.gitignore
.mailmap
.readthedocs.yaml
CHANGES.rst
CITATION
CODE_OF_CONDUCT.md
DESCRIPTION.rst
LICENSE
MANIFEST.in
README.md
mysim_result.fits
pyproject.toml
setup.cfg
setup.py
tox.ini
.github/dependabot.yml
.github/workflows/ci_tests.yml
docs/Makefile
docs/changelog.rst
docs/conf.py
docs/contributing.rst
docs/conventions.rst
docs/credits.rst
docs/design.rst
docs/examples.rst
docs/index.rst
docs/install.rst
docs/licenses.rst
docs/missions.rst
docs/newopticalelements.rst
docs/optics.rst
docs/requirements.txt
docs/results.rst
docs/runexample.rst
docs/source.rst
docs/support.rst
docs/utils.rst
docs/visualization.rst
docs/_static/ex_pol.x3d
docs/_static/notes.txt
docs/_static/subaperturing.x3d
docs/_static/x3dom.css
docs/_static/x3dom.js
docs/_templates/layout.html
docs/_templates/autosummary/base.rst
docs/_templates/autosummary/class.rst
docs/_templates/autosummary/module.rst
docs/design/rowland.rst
docs/design/tolerancing.rst
docs/design/uncertainties.rst
examples/chandra.py
examples/mlmirror.py
licenses/BSD_LICENSE.rst
licenses/LICENSE.rst
marxs/CITATION
marxs/__init__.py
marxs/_astropy_init.py
marxs/conftest.py
marxs/utils.py
marxs/version.py
marxs.egg-info/PKG-INFO
marxs.egg-info/SOURCES.txt
marxs.egg-info/dependency_links.txt
marxs.egg-info/not-zip-safe
marxs.egg-info/requires.txt
marxs.egg-info/top_level.txt
marxs/analysis/__init__.py
marxs/analysis/analysis.py
marxs/analysis/coords.py
marxs/analysis/gratings.py
marxs/analysis/plots.py
marxs/analysis/run_helpers.py
marxs/analysis/tests/__init__.py
marxs/analysis/tests/test_analysis.py
marxs/analysis/tests/test_coords.py
marxs/analysis/tests/test_grating.py
marxs/base/__init__.py
marxs/base/base.py
marxs/base/test/__init__.py
marxs/base/test/test_base.py
marxs/design/__init__.py
marxs/design/bendgratings.py
marxs/design/rowland.py
marxs/design/tolerancing.py
marxs/design/uncertainties.py
marxs/design/tests/__init__.py
marxs/design/tests/test_design.py
marxs/design/tests/test_tolerancing.py
marxs/design/tests/test_uncertainties.py
marxs/design/tests/data/wiggle_global.fits
marxs/math/__init__.py
marxs/math/geometry.py
marxs/math/pluecker.py
marxs/math/polarization.py
